{
  "TopBar": [
    {
      "url": "features",
      "title!": "Features",
      "title": "특징"
    },
    {
      "url": "docs",
      "title!": "Docs",
      "title": "문서"
    },
    {
      "url": "resources",
      "title!": "Resources",
      "title": "리소스"
    },
    {
      "url": "events",
      "title!": "Events",
      "title": "행사 정보"
    },
    {
      "url": "https://blog.angular.io/",
      "title!": "Blog",
      "title": "블로그"
    }
  ],
  "TopBarNarrow": [
    {
      "title!": "About Angular",
      "title": "Angular",
      "children": [
        {
          "url": "features",
          "title!": "Features",
          "title": "특징"
        },
        {
          "url": "resources",
          "title!": "Resources",
          "title": "리소스"
        },
        {
          "url": "events",
          "title!": "Events",
          "title": "행사 정보"
        },
        {
          "url": "https://blog.angular.io/",
          "title!": "Blog",
          "title": "블로그"
        }
      ]
    }
  ],
  "SideNav": [
    {
      "url": "docs",
      "title!": "Introduction",
      "title": "문서",
      "tooltip!": "Introduction to the Angular documentation",
      "tooltip": "Angular 문서 소개",
      "hidden": false
    },
    {
      "url": "guide/docs-style-guide",
      "title!": "Doc authors style guide",
      "title": "문서 편집 가이드",
      "tooltip!": "Style guide for documentation authors.",
      "tooltip": "문서 편집 가이드",
      "hidden": true
    },
    {
      "title!": "Getting Started",
      "title": "시작하기",
      "tooltip!": "Learn the basics by building your first Angular application.",
      "tooltip": "Angular 애플리케이션의 기본 구성 요소에 대해 알아보세요.",
      "children": [
        {
          "url": "start",
          "title!": "Your First App",
          "title": "첫번째 앱 만들기",
          "tooltip!": "Introduction to Angular's component model, template syntax, and component communication.",
          "tooltip": "Angular의 컴포넌트 모델, 템플릿 문법, 컴포넌트끼리 통신하는 방법에 대해 소개합니다."
        },
        {
          "url": "start/routing",
          "title!": "Routing",
          "title": "라우팅",
          "tooltip!": "Introduction to routing between components using the browser's URL.",
          "tooltip": "브라우저 URL에 따라 컴포넌트를 전환하는 방법에 대해 소개합니다."
        },
        {
          "url": "start/data",
          "title!": "Managing Data",
          "title": "데이터 다루기",
          "tooltip!": "Introduction to services and accessing external data via HTTP.",
          "tooltip": "서비스를 사용해서 HTTP 프로토콜로 외부와 데이터 통신하는 방법에 대해 소개합니다."
        },
        {
          "url": "start/forms",
          "title!": "Forms",
          "title": "폼",
          "tooltip!": "Learn about fetching and managing data from users with forms.",
          "tooltip": "사용자가 입력하는 데이터를 폼으로 처리하는 방법에 대해 소개합니다."
        },
        {
          "url": "start/deployment",
          "title!": "Deployment",
          "title": "배포",
          "tooltip!": "Move to local development, or deploy your application to Firebase or your own server.",
          "tooltip": "로컬 개발환경을 설정하는 방법, Firebase나 자체 서버에 애플리케이션을 배포하는 방법에 대해 소개합니다."
        }
      ]
    },
    {
      "url": "guide/setup-local",
      "title!": "Setup",
      "title": "환경설정",
      "tooltip!": "Setting up for local development with the Angular CLI.",
      "tooltip": "Angular CLI로 로컬 개발환경을 설정해 보세요."
    },
    {
      "title!": "Fundamentals",
      "title": "기초 지식",
      "tooltip!": "The fundamentals of Angular",
      "tooltip": "Angular 기초 지식",
      "children": [
        {
          "title!": "Tour of Heroes App",
          "title": "히어로들의 여행 앱",
          "tooltip!": "The Tour of Heroes app is used as a reference point in many Angular examples.",
          "tooltip": "히어로들의 여행 앱을 자세하게 살펴보면서 Angular에 대해 알아봅시다.",
          "children": [
          {
            "url": "tutorial",
            "title!": "Introduction",
            "title": "소개",
            "tooltip!": "Introduction to the Tour of Heroes tutorial",
            "tooltip": "히어로들의 여행 튜토리얼 앱에 대해 소개합니다."
          },
          {
            "url": "tutorial/toh-pt0",
            "title!": "The Application Shell",
            "title": "애플리케이션 기본 틀",
            "tooltip!": "Creating the application shell",
            "tooltip": "애플리케이션 기본 틀을 만들어 봅시다."
          },
          {
            "url": "tutorial/toh-pt1",
            "title!": "1. The Hero Editor",
            "title": "1. 히어로 편집기",
            "tooltip!": "Part 1: Build a simple hero editor",
            "tooltip": "1단계: 간단한 히어로 편집기를 만들어 봅시다."
          },
          {
            "url": "tutorial/toh-pt2",
            "title!": "2. Displaying a List",
            "title": "2. 목록 표시하기",
            "tooltip!": "Part 2: Build a master/detail page with a list of heroes.",
            "tooltip": "2단계: 히어로의 목록을 표시하는 마스터/상세정보 페이지를 만들어 봅시다."
          },
          {
            "url": "tutorial/toh-pt3",
            "title!": "3. Master/Detail Components",
            "title": "3. 마스터/상세정보 컴포넌트",
            "tooltip!": "Part 3: Refactor the master/detail view into separate components.",
            "tooltip": "3단계: 마스터/상세정보 화면을 개별 컴포넌트로 리팩토링해 봅시다."
          },
          {
            "url": "tutorial/toh-pt4",
            "title!": "4. Services",
            "title": "4. 서비스",
            "tooltip!": "Part 4: Create a reusable service to manage hero data.",
            "tooltip": "4단계: 히어로 데이터를 처리하는 로직은 재사용할 수 있게 서비스로 만들어 봅시다."
          },
          {
            "url": "tutorial/toh-pt5",
            "title!": "5. Routing",
            "title": "5. 라우팅",
            "tooltip!": "Part 5: Add the Angular router and navigate among the views.",
            "tooltip": "5단계: Angular 라우터를 추가하고 화면을 전환해 봅시다."
          },
          {
            "url": "tutorial/toh-pt6",
            "title": "6. HTTP",
            "tooltip!": "Part 6: Use HTTP to retrieve and save hero data.",
            "tooltip": "6단계: HTTP 통신으로 히어로 데이터를 가져오고 저장해 봅시다."
          }
          ]
        },
        {
          "title!": "Architecture",
          "title": "아키텍처",
          "tooltip!": "The basic building blocks of Angular applications.",
          "tooltip": "Angular 애플리케이션을 구성하는 기본 요소에 대해 알아봅시다.",
          "children": [
            {
              "url": "guide/architecture",
              "title!": "Architecture Overview",
              "title": "개요",
              "tooltip!": "Basic building blocks of Angular applications.",
              "tooltip": "Angular 애플리케이션을 구성하는 기본 요소"
            },
            {
              "url": "guide/architecture-modules",
              "title!": "Intro to Modules",
              "title": "모듈",
              "tooltip!": "About NgModules.",
              "tooltip": "NgModule 소개"
            },
            {
              "url": "guide/architecture-components",
              "title!": "Intro to Components",
              "title": "컴포넌트",
              "tooltip!": "About Components, Templates, and Views.",
              "tooltip": "컴포넌트, 템플릿, 뷰"
            },
            {
              "url": "guide/architecture-services",
              "title!": "Intro to Services and DI",
              "title": "서비스, 의존성 주입",
              "tooltip!": "About services and dependency injection.",
              "tooltip": "서비스와 의존성 주입"
            },
            {
              "url": "guide/architecture-next-steps",
              "title!": "Next Steps",
              "title": "다음 단계",
              "tooltip!": "Beyond the basics.",
              "tooltip": "심화"
            }
          ]
        },
        {
          "title!": "Components & Templates",
	        "title": "컴포넌트 & 템플릿",
          "tooltip!": "Building dynamic views with data binding",
          "tooltip": "데이터 바인딩으로 뷰를 동적으로 구성해 보세요.",
          "children": [
            {
              "url": "guide/displaying-data",
              "title!": "Displaying Data",
              "title": "데이터 표시하기",
              "tooltip!": "Property binding helps show app data in the UI.",
              "tooltip": "UI에 데이터 바인딩하기"
            },
            {
              "url": "guide/template-syntax",
              "title!": "Template Syntax",
              "title": "템플릿 문법",
              "tooltip!": "Learn how to write templates that display data and consume user events with the help of data binding.",
              "tooltip": "템플릿에 데이터를 어떻게 표시하는지, 이벤트를 어떻게 처리하는지 알아봅니다."
            },
            {
              "url": "guide/user-input",
              "!title": "User Input",
              "title": "사용자 동작",
              "!tooltip": "User input triggers DOM events. Angular listens to those events with event bindings that funnel updated values back into your app's components and models.",
              "tooltip": "사용자가 애플리케이션을 실행할 때 DOM 이벤트가 발생합니다. Angular는 이 이벤트를 사용해서 애플리케이션 컴포넌트와 모델을 갱신합니다."
            },
            {
              "url": "guide/lifecycle-hooks",
              "title!": "Lifecycle Hooks",
              "title": "라이프싸이클 후킹",
              "tooltip!": "Angular calls lifecycle hook methods on directives and components as it creates, changes, and destroys them.",
              "tooltip": "Angular 디렉티브와 컴포넌트는 라이프싸이클 후킹 함수를 지원합니다."
            },
            {
              "url": "guide/component-interaction",
              "title!": "Component Interaction",
              "title": "컴포넌트 통신",
              "tooltip!": "Share information between different directives and components.",
              "tooltip": "디렉티브와 컴포넌트끼리 데이터를 전달할 수 있습니다."
            },
            {
              "url": "guide/component-styles",
              "title!": "Component Styles",
	            "title": "컴포넌트 스타일",
              "tooltip!": "Add CSS styles that are specific to a component.",
	            "tooltip": "CSS 스타일을 추가해서 컴포넌트를 꾸밀 수 있습니다."
            },
            {
              "url": "guide/elements",
              "title": "Angular Elements",
              "tooltip!": "Convert components to Custom Elements.",
              "tooltip": "컴포넌트를 커스텀 엘리먼트로 활용하세요."
            },
            {
              "url": "guide/dynamic-component-loader",
              "title!": "Dynamic Components",
	            "title": "동적 컴포넌트",
              "tooltip!": "Load components dynamically.",
              "tooltip": "컴포넌트를 동적으로 불러올 수 있습니다."
            },
            {
              "url": "guide/attribute-directives",
              "title!": "Attribute Directives",
              "title": "어트리뷰트 디렉티브",
              "tooltip!": "Attribute directives attach behavior to elements.",
              "tooltip": "어트리뷰트 디렉티브는 DOM 엘리먼트의 속성을 정의합니다."
            },
            {
              "url": "guide/structural-directives",
              "title!": "Structural Directives",
              "title": "구조 디렉티브",
              "tooltip!": "Structural directives manipulate the layout of the page.",
              "tooltip": "페이지의 레이아웃을 조작하는 구조 디렉티브에 대해 알아봅니다."
            },
            {
              "url": "guide/pipes",
              "title!": "Pipes",
              "title": "파이프",
              "tooltip!": "Pipes transform displayed values within a template.",
              "tooltip": "파이프는 템플릿에 표시되는 데이터의 형식을 지정합니다."
            }
          ]
        },
        {
          "title!": "Forms",
          "title": "폼",
          "tooltip!": "Angular Forms",
          "tooltip": "Angular 폼",
          "children": [
            {
              "url": "guide/forms-overview",
              "!title": "Introduction",
              "title": "폼 소개",
              "tooltip!": "A form creates a cohesive, effective, and compelling data entry experience. An Angular form coordinates a set of data-bound user controls, tracks changes, validates input, and presents errors.",
	            "tooltip": "폼을 구성하면 사용자 입력을 일관되고 효율적으로 처리할 수 있습니다. Angular 폼은 입력 컨트롤을 묶어서 구성하고, 변화를 감지하며, 입력값의 유효성을 판단하고 에러를 표시할 수 있습니다."
            },
            {
              "url": "guide/reactive-forms",
              "!title": "Reactive Forms",
              "title": "반응형 폼",
              "!tooltip": "Create a reactive form using FormBuilder, groups, and arrays.",
              "tooltip": "FormBuilder, 그룹, 배열을 사용해서 반응형 폼을 만들어 보세요."
            },
            {
              "url": "guide/forms",
              "!title": "Template-driven Forms",
              "title": "템플릿 기반 폼",
              "!tooltip": "Create a template-driven form using directives and Angular template syntax.",
              "tooltip": "디렉티브와 Angular 템플릿 문법을 활용해서 템플릿 기반 폼을 만들어 보세요."
            },
            {
              "url": "guide/form-validation",
              "title!": "Form Validation",
              "title": "폼 유효성 검사",
              "tooltip!": "Validate user's form entries.",
              "tooltip": "사용자가 입력한 폼의 유효성을 검사합니다."
            },
            {
              "url": "guide/dynamic-form",
              "!title": "Dynamic Forms",
              "title": "동적 폼",
              "!tooltip": "Render dynamic forms with FormGroup.",
              "tooltip": "FormGroup으로 동적 폼을 구성해 보세요."
            }
          ]
        },
        {
          "!title": "Observables & RxJS",
          "title": "옵저버블 & RxJS",
          "!tooltip": "Observables & RxJS",
          "tooltip": "옵저버블 & RxJS",
          "children": [
            {
              "url": "guide/observables",
              "title!": "Observables",
              "title": "옵저버블",
              "tooltip": ""
            },
            {
              "url": "guide/rx-library",
              "title!": "The RxJS Library",
              "title": "RxJS 라이브러리",
              "tooltip": ""
            },
            {
              "url": "guide/observables-in-angular",
              "title!": "Observables in Angular",
              "title": "Angular에서 옵저버블 활용하기",
              "tooltip": ""
            },
            {
              "url": "guide/practical-observable-usage",
              "title!": "Practical Usage",
              "title": "실전 예제",
              "tooltip": ""
            },
            {
              "url": "guide/comparing-observables",
              "title!": "Compare to Other Techniques",
              "title": "다른 방식과 비교",
              "tooltip": ""
            }
          ]
        },
        {
          "url": "guide/bootstrapping",
          "title!": "Bootstrapping",
          "title": "부트스트랩",
          "tooltip!": "Tell Angular how to construct and bootstrap the app in the root \"AppModule\".",
          "tooltip": "Angular가 \"AppModule\"을 어떻게 구성하고 실행하는지 알아봅니다."
        },
        {
          "title": "NgModule",
          "tooltip": "NgModule",
          "children": [
            {
              "url": "guide/ngmodules",
              "title!": "NgModules Introduction",
              "title": "NgModule 소개",
              "tooltip!": "Use NgModules to make your apps efficient.",
              "tooltip": "앱을 효율적으로 구현하려면 NgModule을 사용하세요."
            },
            {
              "url": "guide/ngmodule-vs-jsmodule",
              "title!": "JS Modules vs NgModules",
              "title": "JS 모듈 vs NgModule",
              "tooltip!": "Differentiate between JavaScript modules and NgModules.",
              "tooltip": "JavaScript 모듈과 NgModule의 차이점을 알아봅니다."
            },
            {
              "url": "guide/frequent-ngmodules",
              "title!": "Frequently Used NgModules",
              "title": "자주 사용하는 NgModule",
              "tooltip!": "Introduction to the most frequently used NgModules.",
              "tooltip": "자주 사용하는 NgModule을 알아봅니다."
            },
            {
              "url": "guide/module-types",
              "title!": "Types of Feature Modules",
              "title": "기능 모듈의 종류",
              "tooltip!": "Description of the different types of feature modules.",
              "tooltip": "기능 모듈의 종류에 대해 알아봅니다."
            },
            {
              "url": "guide/entry-components",
              "title!": "Entry Components",
              "title": "진입 컴포넌트",
              "tooltip!": "All about entry components in Angular.",
              "tooltip": "진입 컴포넌트가 어떤 것인지 알아봅니다."
            },
            {
              "url": "guide/feature-modules",
              "title!": "Feature Modules",
              "title": "기능 모듈",
              "tooltip!": "Create feature modules to organize your code.",
              "tooltip": "코드를 효율적으로 구성하는 기능 모듈을 만들어 봅니다."
            },
            {
              "url": "guide/providers",
              "title!": "Providers",
              "title": "프로바이더",
              "tooltip!": "Providers and NgModules.",
              "tooltip": "프로바이더와 NgModule"
            },
            {
              "url": "guide/singleton-services",
              "title!": "Singleton Services",
              "title": "싱글턴 서비스",
              "tooltip!": "Creating singleton services.",
              "tooltip": "서비스를 싱글턴으로 만들어 봅니다."
            },
            {
              "url": "guide/lazy-loading-ngmodules",
              "title!": "Lazy Loading Feature Modules",
              "title": "기능모듈 지연로딩하기",
              "tooltip!": "Lazy load modules to speed up your apps.",
              "tooltip": "모듈을 지연 로딩 하면 앱 초기 실행 속도를 향상시킬 수 있습니다."
            },
            {
              "url": "guide/sharing-ngmodules",
              "title!": "Sharing NgModules",
              "title": "모듈 공유하기",
              "tooltip!": "Share NgModules to streamline your apps.",
              "tooltip": "앱 전반에 NgModule을 공유해 보세요."
            },
            {
              "url": "guide/ngmodule-api",
              "title": "NgModule API",
              "tooltip!": "Understand the details of NgModules.",
              "tooltip": "NgModule에서 제공하는 API를 좀 더 자세하게 알아봅니다."
            },
            {
              "url": "guide/ngmodule-faq",
              "title": "NgModule FAQs",
              "tooltip!": "Answers to frequently asked questions about NgModules.",
              "tooltip": "NgModule에 대해 자주 물어보는 질문"
            }
          ]
        },
        {
          "title!": "Dependency Injection",
          "title": "의존성 주입",
          "tooltip": "Dependency Injection: creating and injecting services",
          "tooltip": "의존성 주입: 서비스 만들고 의존성으로 주입하기",
          "children": [
            {
              "url": "guide/dependency-injection",
              "title!": "Angular Dependency Injection",
              "title": "Angular의 의존성 주입",
              "tooltip!": "Angular's dependency injection system creates and delivers dependent services to Angular-created classes.",
              "tooltip": "Angular는 의존성으로 주입하는 클래스를 직접 만들어서 목표 클래스에 주입합니다."
            },
            {
              "url": "guide/hierarchical-dependency-injection",
              "!title": "Hierarchical Injectors",
              "title": "인젝터 계층",
              "tooltip": "An injector tree parallels the component tree and supports nested dependencies.",
              "!tooltip": "인젝터는 컴포넌트 트리와 동일하게 트리 형태로 구성됩니다."
            },
            {
              "url": "guide/dependency-injection-providers",
              "!title": "DI Providers",
              "title": "의존성 주입 프로바이더",
              "!tooltip": "More about the different kinds of providers.",
              "tooltip": "프로바이더의 종류에 대해 알아보세요."
            },
            {
              "url": "guide/dependency-injection-in-action",
              "!title": "DI in Action",
              "title": "실전 의존성 주입",
              "!tooltip": "Techniques for dependency injection.",
              "tooltip": "의존성 주입 테크닉에 대해 알아보세요."
            },
            {
              "url": "guide/dependency-injection-navtree",
              "!title": "Navigate the Component Tree",
              "title": "컴포넌트 트리 참조하기",
              "!tooltip": "Use the injection tree to find parent components.",
              "tooltip": "인젝터 트리를 활용하면 부모 컴포넌트를 참조할 수 있습니다."
            }
          ]
        },
        {
          "url": "guide/http",
          "title": "HttpClient",
          "tooltip!": "Use HTTP to talk to a remote server.",
          "tooltip": "서버와 HTTP 통신하기"
        },
        {
          "url": "guide/router",
          "title!": "Routing & Navigation",
          "title": "라우팅 & 네비게이션",
          "tooltip!": "Discover the basics of screen navigation with the Angular Router.",
          "tooltip": "Angular 라우터를 사용해서 화면을 전환할 수 있습니다."
        },
        {
          "!title": "Animations",
          "title": "애니메이션",
          "!tooltip": "A guide to Angular's animation system.",
          "tooltip": "Angular 애니메이션 시스템에 대해 알아보세요.",
          "children": [
            {
              "url": "guide/animations",
              "!title": "Introduction",
              "title": "소개",
              "!tooltip": "Basic techniques in Angular animations.",
              "tooltip": "Angular 애니메이션 기초"
            },
            {
              "url": "guide/transition-and-triggers",
              "!title": "Transition and Triggers",
              "title": "트랜지션 & 트리거",
              "!tooltip": "Advanced techniques in transition and triggers.",
              "tooltip": "트랜지션과 트리거를 활용하는 테크닉"
            },
            {
              "url": "guide/complex-animation-sequences",
              "!title": "Complex Sequences",
              "title": "복잡한 시퀀스 처리하기",
              "!tooltip": "Complex Angular animation sequences.",
              "tooltip": "복잡한 애니메이션 시퀀스도 구현할 수 있습니다."
            },
            {
              "url": "guide/reusable-animations",
              "!title": "Reusable Animations",
              "title": "애니메이션 재사용하기",
              "!tooltip": "Creating reusable animations.",
              "tooltip": "재사용할 수 있는 애니메이션을 정의해 보세요."
            },
            {
              "url": "guide/route-animations",
              "!title": "Route Transition Animations",
              "title": "페이지 전환 애니메이션",
              "!tooltip": "Animate route transitions.",
              "tooltip": "페이지를 전환할 때도 애니메이션을 사용할 수 있습니다."
            }
          ]
        }
      ]
    },
    {
      "title!": "Techniques",
      "title": "고급",
      "tooltip!": "Techniques for putting Angular to work in your environment",
      "tooltip": "Angular를 실제 프로젝트에 더 활용할 수 있는 방법에 대해 안내합니다.",
      "children": [
        {
          "url": "guide/security",
          "title!": "Security",
          "title": "보안",
          "tooltip!": "Developing for content security in Angular applications.",
          "tooltip": "Angular 애플리케이션에 보안 기능 적용하기"
        },
        {
          "url": "guide/i18n",
          "title": "Internationalization (i18n)",
          "tooltip": "Translate the app's template text into multiple languages."
        },
        {
          "!title": "Service Workers & PWA",
          "title": "서비스 워커 & PWA",
          "!tooltip": "Angular service workers: Controlling caching of application resources.",
          "tooltip": "Angular 서비스 워커: 애플리케이션 리소스를 캐싱할 수 있습니다.",
          "children": [
            {
              "url": "guide/service-worker-intro",
              "title!": "Introduction",
              "title": "소개",
              "tooltip!": "Angular's implementation of service workers improves user experience with slow or unreliable network connectivity.",
              "tooltip": "Angular가 제공하는 서비스 워커에 대해 알아봅니다. 서비스 워커를 활용하면 네트워크 연결이 원활하지 않은 곳에서도 앱 사용성을 유지할 수 있습니다."
            },
            {
              "url": "guide/service-worker-getting-started",
              "title!": "Getting Started",
              "title": "시작하기",
              "tooltip!": "Enabling the service worker in a CLI project and observing behavior in the browser.",
              "tooltip": "CLI로 Angular 프로젝트를 만들면서 서비스 워커를 시작할 수 있습니다. 브라우저에서 서비스 워커 동작을 확인할 수도 있습니다."
            },
            {
              "url": "guide/app-shell",
              "!title": "App Shell",
              "title": "앱 기본 틀",
              "!tooltip": "Enabling the App Shell in a CLI project.",
              "tooltip": "애플리케이션 기본 틀 생성하기"
            },
            {
              "url": "guide/service-worker-communications",
              "title!": "Service Worker Communication",
              "title": "서비스 워커 통신",
              "tooltip!": "Services that enable you to interact with an Angular service worker.",
              "tooltip": "서비스 워커를 사용하는 Angular 서비스 만들기"
            },
            {
              "url": "guide/service-worker-devops",
              "title!": "Service Worker in Production",
              "title": "서비스 워커 활용",
              "tooltip!": "Running applications with service workers, managing application update, debugging, and killing applications.",
              "tooltip": "서비스 워커를 사용해서 애플리케이션을 실행하고, 애플리케이션을 업데이트 할 수 있습니다. 애플리케이션을 디버깅하거나 종료할 수도 있습니다."
            },
            {
              "url": "guide/service-worker-config",
              "title!": "Service Worker Configuration",
              "title": "서비스 워커 설정",
              "tooltip!": "Configuring service worker caching behavior.",
              "tooltip": "서비스 워커 캐시 설정하기"
            }
          ]
        },
        {
          "url": "guide/universal",
          "!title": "Server-side Rendering",
          "title": "서버 사이드 렌더링",
          "!tooltip": "Render HTML server-side with Angular Universal.",
          "tooltip": "Angular Universal을 사용하면 서버에 HTML 문서를 렌더링 해둘 수 있습니다."
        },
        {
          "title!": "Upgrading from AngularJS",
          "title": "업그레이드",
          "tooltip!": "Incrementally upgrade an AngularJS application to Angular.",
          "tooltip": "AngularJS 애플리케이션을 Angular로 업그레이드 하세요.",
          "children": [
            {
              "url": "guide/upgrade",
              "title!": "Upgrading Instructions",
              "title": "AngularJS 앱 업그레이드하기",
              "tooltip!": "Incrementally upgrade an AngularJS application to Angular.",
              "tooltip": "AngularJS 애플리케이션을 Angular로 업그레이드 하세요."
            },
            {
              "url": "guide/upgrade-performance",
              "title!": "Upgrading for Performance",
              "title": "성능 향상",
              "tooltip!": "Upgrade from AngularJS to Angular in a more flexible way.",
              "tooltip": "AngularJS 프로젝트를 그대로 실행하면서 Angular 프로젝트로 점차적으로 도입할 수 있습니다."
            },
            {
              "url": "guide/ajs-quick-reference",
              "title!": "AngularJS-Angular Concepts",
              "title": "AngularJS와 Angular 컨셉 비교",
              "tooltip!": "Learn how AngularJS concepts and techniques map to Angular.",
              "tooltip": "AngularJS에서 사용하는 컨셉과 테크닉을 Angular에 어떻게 적용할 수 있는지 확인해 보세요."
            }
          ]
        },
        {
          "title!": "Angular Libraries",
          "title": "Angular 라이브러리",
          "tooltip!": "Extending Angular with shared libraries.",
          "tooltip": "다른 개발자가 공유한 라이브러리로 Angular는 확장해보세요.",
          "children": [
            {
              "url": "guide/libraries",
              "title!": "Libraries Overview",
              "title": "개요",
              "tooltip!": "Understand how and when to use or create libraries.",
              "tooltip": "라이브러리는 언제 만들고 어떻게 사용하는지 알아봅시다."
            },
            {
              "url": "guide/using-libraries",
              "title!": "Using Published Libraries",
              "title": "공유된 라이브러리 사용하기",
              "tooltip!": "Integrate published libraries into an app.",
              "tooltip": "공유된 라이브러리를 앱에 추가해 봅시다."
            },
            {
              "url": "guide/creating-libraries",
              "title!": "Creating Libraries",
              "title": "라이브러리 만들기",
              "tooltip!": "Extend Angular by creating, publishing, and using your own libraries.",
              "tooltip": "라이브러리를 만들고 배포해서 Angular 생태계를 직접 확장해 보세요."
            }
          ]
        },
        {
          "title!": "Schematics",
          "title": "스키매틱",
          "tooltip!": "Understanding schematics.",
          "tooltip": "스키매틱 이해하기",
          "children": [
            {
              "url": "guide/schematics",
              "title!": "Schematics Overview",
              "title": "스키매틱 소개",
              "tooltip!": "Understand how schematics are used in Angular.",
              "tooltip": "Angular에서 스키매틱이 어떻게 사용되는지 알아봅시다."
            },
            {
              "url": "guide/schematics-authoring",
              "title!": "Authoring Schematics",
              "title": "스키매틱 정의하기",
              "tooltip!": "Understand the structure of a schematic.",
              "tooltip": "스키매틱을 구성하는 요소에 대해 알아봅시다."
            },
            {
              "url": "guide/schematics-for-libraries",
              "title!": "Schematics for Libraries",
              "title": "스키매틱을 라이브러리로 사용하기",
              "tooltip!": "Use schematics to integrate your library with the Angular CLI.",
              "tooltip": "Angular CLI를 사용해서 스키매틱을 라이브러리처럼 사용해 보세요."
            }
          ]
        },
        {
          "url": "guide/cli-builder",
          "title!": "CLI Builders",
          "title": "CLI 빌더",
          "tooltip!": "Using builders to customize Angular CLI.",
          "tooltip": "빌더를 사용해서 Angular CLI를 커스터마이징 해보세요."
        },
        {
          "url": "guide/ivy",
          "title": "Angular Ivy",
          "tooltip!": "Opting into Angular Ivy with Angular CLI.",
          "tooltip": "Angular CLI를 사용해서 Angular Ivy를 도입해 보세요."
        },
        {
          "url": "guide/web-worker",
          "title!": "Web Workers",
          "title": "웹 워커",
          "tooltip!": "Using Web Workers with Angular CLI.",
          "tooltip": "Angular CLI를 사용해서 웹 워커를 도입해 보세요."
        }
      ]
    },
    {
      "title!": "Dev Workflow",
      "title": "개발 단계",
      "tooltip!": "Build, testing, and deployment information.",
      "tooltip": "빌드, 테스트, 배포 과정에 대해 설명합니다.",
      "children": [
        {
          "url": "guide/setup",
          "title": "Upgrade setup",
          "tooltip": "How to set up the Angular QuickStart seed in the context of upgrading from AngularJS.",
          "hidden": true
        },
        {
          "url": "guide/aot-compiler",
          "!title": "Ahead-of-Time Compilation",
          "title": "AOT 컴파일러",
          "!tooltip": "Learn why and how to use the Ahead-of-Time (AOT) compiler.",
          "tooltip": "AOT 컴파일러를 사용하는 이유와 활용 방법에 대해 안내합니다."
        },
        {
          "url": "guide/build",
          "!title": "Building & Serving",
          "title": "프로젝트 빌드/실행 설정",
          "!tooltip": "Building and serving Angular apps.",
          "tooltip": "Angular 앱을 개발용, 운영용으로 빌드해 보세요."
        },
        {
          "url": "guide/bazel",
          "title!": "Building with Bazel",
          "title": "Bazel로 빌드하기",
          "tooltip!": "How to set up your environment to build and test with Bazel.",
          "tooltip": "Bazel을 사용한 빌드 환경을 어떻게 구성하는지, 이 환경에서 테스트는 어떻게 실행하는지 안내합니다."
        },
        {
          "url": "guide/testing",
          "!title": "Testing",
          "title": "테스트",
          "!tooltip": "Techniques and practices for testing an Angular app.",
          "tooltip": "Angular 앱에 테스트를 적용하는 방법에 대해 안내합니다."
        },
        {
          "url": "guide/deployment",
          "!title": "Deployment",
          "title": "배포",
          "!tooltip": "Learn how to deploy your Angular app.",
          "tooltip": "Angular 앱을 배포하는 방법에 대해 안내합니다."
        },
        {
          "title!": "Dev Tool Integration",
          "title": "개발 툴 지원",
          "tooltip!": "Integrate with your development environment and tools.",
          "tooltip": "개발 환경과 툴에 적용할 수 있는 Angular 지원 기능에 대해 안내합니다.",
          "children": [
            {
              "url": "guide/language-service",
              "title!": "Language Service",
              "title": "언어 지원 서비스",
              "tooltip!": "Use Angular Language Service to speed up dev time.",
              "tooltip": "Angular 언어 지원 서비스를 활용하면 개발 속도를 빠르게 향상시킬 수 있습니다."
            },
            {
              "url": "guide/visual-studio-2015",
              "title": "Visual Studio 2015",
              "tooltip": "Using Angular with Visual Studio 2015.",
              "hidden": true
            }
          ]
        }
      ]
    },
    {
      "title!": "Configuration",
      "title": "개발환경 설정",
      "tooltip!": "Workspace and project structure, configuration files.",
      "tooltip": "워크스페이스와 프로젝트 구조, 환경설정 파일에 대해 안내합니다.",
      "children": [
        {
          "url": "guide/file-structure",
          "title!": "Project File Structure",
          "title": "프로젝트 파일 구조",
          "tooltip!": "How your Angular workspace looks on your filesystem.",
          "tooltip": "Angular 워크스페이스는 어떤 구조인지 확인해 봅시다."
        },
        {
          "url": "guide/workspace-config",
          "title!": "Workspace Configuration",
          "title": "워크스페이스 설정",
          "tooltip!": "The \"angular.json\" file contains workspace and project configuration defaults for Angular CLI commands.",
          "tooltip": "워크스페이스와 프로젝트 환경에서 동작하는 Angular CLI 명령의 기본값을 설정하는 \"angular.json\" 파일에 대해 알아봅시다."
        },
        {
          "url": "guide/npm-packages",
          "title!": "npm Dependencies",
          "title": "npm 의존성 패키지",
          "tooltip!": "Description of npm packages required at development time and at runtime.",
          "tooltip": "개발 환경과 실행 환경에 필요한 npm 패키지들에 대해 알아봅시다."
        },
        {
          "url": "guide/typescript-configuration",
          "title!": "TypeScript Configuration",
          "title": "TypeScript 설정",
          "tooltip!": "TypeScript configuration for Angular developers.",
          "tooltip": "Angular 코드에 적용되는 TypeScript 설정에 대해 알아봅시다."
        },
        {
          "url": "guide/browser-support",
          "title!": "Browser Support",
          "title": "브라우저 지원",
          "tooltip!": "Browser support and polyfills guide.",
          "tooltip": "브라우저 지원과 폴리필 가이드에 대해 안내합니다."
        }
      ]
    },
    {
      "!title": "Release Information",
      "title": "릴리즈 정보",
      "!tooltip": "Angular release practices, updating, and upgrading.",
      "tooltip": "Angular 릴리즈에 대응하는 방법을 안내합니다.",
      "children": [
        {
          "url": "guide/updating",
           "!title": "Keeping Up-to-Date",
           "title": "최신 버전 적용하기",
           "!tooltip": "Information about updating Angular applications and libraries to the latest version.",
           "tooltip": "Angular 프레임워크를 최신 버전으로 업데이트하는 방법을 안내합니다."
        },
        {
          "url": "guide/releases",
          "!title": "Release Practices",
          "title": "릴리즈 정책",
          "!tooltip": "Angular versioning, release, support, and deprecation policies and practices.",
          "tooltip": "Angular 버전 정책, 릴리즈 주기, 지원 정책, 지원 중단 정책에 대해 안내합니다."
        },
        {
          "url": "guide/deprecations",
          "title!": "Deprecations",
          "title": "지원 중단 기능",
          "tooltip!": "Summary of Angular APIs and features that are deprecated.",
          "tooltip": "지원이 중단되는 Angular API와 기능에 대해 알아봅시다."
        }
      ]
    },
    {
      "!title": "Quick Reference",
      "title": "참고",
      "!tooltip": "Summaries of Angular syntax, coding, and terminology.",
      "tooltip": "Angular의 문법, 코딩 패턴, 기술에 대한 요약본을 제공합니다.",
      "children": [
        {
          "url": "guide/cheatsheet",
          "!title": "Cheat Sheet",
          "title": "치트 시트",
          "!tooltip": "A quick guide to common Angular coding techniques.",
          "tooltip": "Angular에서 사용하는 문법을 빠르게 훑어보세요."
        },
        {
          "url": "guide/styleguide",
          "title!": "Style Guide",
          "title": "코딩 스타일 가이드",
          "tooltip!": "Write Angular with style.",
          "tooltip": "Angular 코딩 스타일 가이드"
        },
        {
          "url": "guide/glossary",
          "title!": "Glossary",
          "title": "찾아보기",
          "tooltip!": "Brief definitions of the most important words in the Angular vocabulary.",
          "tooltip": "Angular에 자주 나오는 용어를 빠르게 찾아보세요."
        }
      ]
    },
    {
      "!title": "CLI Commands",
      "title": "Angular CLI",
      "!tooltip": "Angular CLI command reference.",
      "tooltip": "Angular CLI 명령에 대해 안내합니다.",
      "children": [
        {
          "!title": "Overview",
          "title": "개요",
          "!tooltip": "An introduction to the CLI tool, commands, and syntax.",
          "tooltip": "Angular CLI 사용방법을 소개합니다.",
          "url": "cli"
        },
        {
          "title!": "Usage Analytics",
          "title": "사용 통계",
          "tooltip!": "For administrators, guide to gathering usage analytics from your users.",
          "tooltip": "사용자들이 앱을 어떻게 사용하는지 통계를 작성할 수 있습니다. 관리자를 위한 기능입니다.",
          "url": "cli/usage-analytics-gathering"
        }
      ]
    },
    {
      "title": "API",
      "!tooltip": "Details of the Angular packages, classes, interfaces, and other types.",
      "tooltip": "Angular 패키지, 클래스, 인터페이스, 타입 정보에 대해 알아보세요.",
      "url": "api"
    }
  ],
  "Footer": [
    {
      "title!": "Resources",
      "title": "리소스",
      "children": [
        {
          "url": "about",
          "title": "About",
          "tooltip!": "Angular contributors.",
          "tooltip": "Angular 컨트리뷰터"
        },
        {
          "url": "resources",
          "title!": "Resource Listing",
          "title": "참고 자료",
          "tooltip!": "Angular tools, training, and blogs from around the web.",
          "tooltip": "Angular 툴, 강좌, 블로그"
        },
        {
          "url": "presskit",
          "title!": "Press Kit",
          "title": "브랜드 자료",
          "tooltip!": "Press contacts, logos, and branding.",
          "tooltip": "Angular 로고, 브랜드 설명"
        },
        {
          "url": "https://blog.angular.io/",
          "title!": "Blog",
          "title": "블로그",
          "tooltip!": "Angular Blog",
          "tooltip": "Angular 블로그"
        },
        {
          "url": "analytics",
          "title": "Usage Analytics",
          "tooltip": "Angular Usage Analytics"
        }
      ]
    },
    {
      "title!": "Help",
      "title": "참고 사이트",
      "children": [
        {
          "url": "https://stackoverflow.com/questions/tagged/angular",
          "title": "Stack Overflow",
          "tooltip!": "Stack Overflow: where the community answers your technical Angular questions.",
          "tooltip": "Stack Overflow: \"Angular\"가 태그된 질문은 Angular 커뮤니티에서 답변을 주기도 합니다."
        },
        {
          "url": "https://gitter.im/angular/angular",
          "title": "Gitter",
          "tooltip!": "Chat about Angular with other birds of a feather.",
          "tooltip": "Angular를 주제로 채팅하기"
        },
        {
          "url": "https://github.com/angular/angular/issues",
          "title!": "Report Issues",
          "title": "이슈 등록하기",
          "tooltip!": "Post issues and suggestions on github.",
          "tooltip": "github에 이슈 등록, 개선 제안하기."
        },
        {
          "url": "https://github.com/angular/code-of-conduct/blob/master/CODE_OF_CONDUCT.md",
          "title!": "Code of Conduct",
          "title": "커뮤니티 활용 수칙",
          "tooltip!": "Treating each other with respect.",
          "tooltip": "친하게 지내요:)"
        }
      ]
    },
    {
      "!title": "Community",
      "title": "커뮤니티",
      "children": [
        {
          "url": "events",
          "title!": "Events",
          "title": "행사일정",
          "tooltip!": "Angular events around the world.",
          "tooltip": "세계 각지에서 열리는 행사 일정 확인하기"
        },
        {
          "url": "http://www.meetup.com/topics/angularjs/",
          "title!": "Meetups",
          "title": "밋업",
          "tooltip!": "Attend a meetup and learn from fellow developers.",
          "tooltip": "Angular 밋업 확인하기"
        },
        {
          "url": "https://twitter.com/angular",
          "title": "Twitter",
          "tooltip": "Twitter"
        },
        {
          "url": "https://github.com/angular/angular",
          "title": "GitHub",
          "tooltip": "GitHub"
        },
        {
          "url": "contribute",
          "title!": "Contribute",
          "title": "개발에 참여하기",
          "tooltip!": "Contribute to Angular",
          "tooltip": "Angular 개발에 참여하기"
        }
      ]
    },
    {
      "!title": "Languages",
      "title": "다른 언어",
      "children": [
        {
          "title": "English",
          "url": "https://angular.io/"
        },
        {
          "title": "中文版",
          "url": "https://angular.cn/"
        },
        {
          "title": "日本語版",
          "url": "https://angular.jp/"
        },
        {
          "title": "한국어",
          "url": "https://angular.kr/"
        }
      ]
    }
  ],
  "docVersions": [
    {
      "title": "v7",
      "url": "https://v7.angular.io/"
    },
    {
      "title": "v6",
      "url": "https://v6.angular.io/"
    },
    {
      "title": "v5",
      "url": "https://v5.angular.io/"
    },
    {
      "title": "v4",
      "url": "https://v4.angular.io/"
    },
    {
      "title": "v2",
      "url": "https://v2.angular.io/"
    }
  ]
}
