{
  "aio": {
    "master": {
      "uncompressed": {
        "runtime-es2015": 2987,
        "main-es2015": 464973,
        "polyfills-es2015": 52503
      }
    }
  },
  "aio-local": {
    "master": {
      "uncompressed": {
        "runtime-es2015": 2987,
        "main-es2015": 506857,
        "polyfills-es2015": 52503
      }
    }
  },
  "aio-local-viewengine": {
    "master": {
      "uncompressed": {
        "runtime-es2015": 3097,
        "main-es2015": 436779,
        "polyfills-es2015": 52503
      }
    }
  }
}
